Metadata-Version: 2.1
Name: ngram-extration
Version: 0.0.3
Summary: 用于提取语料库的最大词频情况下的最长字符串，即用于挖掘语料库中的高频长字符串
Home-page: https://github.com/BiaoLiu2017/ngram_extration
Author: Biao Liu
Author-email: liubiao2017@gmail.com
Classifier: Programming Language :: Python :: 3
Classifier: License :: OSI Approved :: MIT License
Classifier: Operating System :: OS Independent
License-File: LICENSE
